{"name":"mage","allianceHeroes":["CRYSTAL-MAIDEN","KEEPER-OF-THE-LIGHT","LICH","LINA","OGRE-MAGI","PUCK","RAZOR"],"allianceHeroesCount":7,"levels":[{"count":3,"preCombinations":[["CRYSTAL-MAIDEN","KEEPER-OF-THE-LIGHT","LICH"],["CRYSTAL-MAIDEN","KEEPER-OF-THE-LIGHT","LINA"],["CRYSTAL-MAIDEN","KEEPER-OF-THE-LIGHT","OGRE-MAGI"],["CRYSTAL-MAIDEN","KEEPER-OF-THE-LIGHT","PUCK"],["CRYSTAL-MAIDEN","KEEPER-OF-THE-LIGHT","RAZOR"],["CRYSTAL-MAIDEN","LICH","LINA"],["CRYSTAL-MAIDEN","LICH","OGRE-MAGI"],["CRYSTAL-MAIDEN","LICH","PUCK"],["CRYSTAL-MAIDEN","LICH","RAZOR"],["CRYSTAL-MAIDEN","LINA","OGRE-MAGI"],["CRYSTAL-MAIDEN","LINA","PUCK"],["CRYSTAL-MAIDEN","LINA","RAZOR"],["CRYSTAL-MAIDEN","OGRE-MAGI","PUCK"],["CRYSTAL-MAIDEN","OGRE-MAGI","RAZOR"],["CRYSTAL-MAIDEN","PUCK","RAZOR"],["KEEPER-OF-THE-LIGHT","LICH","LINA"],["KEEPER-OF-THE-LIGHT","LICH","OGRE-MAGI"],["KEEPER-OF-THE-LIGHT","LICH","PUCK"],["KEEPER-OF-THE-LIGHT","LICH","RAZOR"],["KEEPER-OF-THE-LIGHT","LINA","OGRE-MAGI"],["KEEPER-OF-THE-LIGHT","LINA","PUCK"],["KEEPER-OF-THE-LIGHT","LINA","RAZOR"],["KEEPER-OF-THE-LIGHT","OGRE-MAGI","PUCK"],["KEEPER-OF-THE-LIGHT","OGRE-MAGI","RAZOR"],["KEEPER-OF-THE-LIGHT","PUCK","RAZOR"],["LICH","LINA","OGRE-MAGI"],["LICH","LINA","PUCK"],["LICH","LINA","RAZOR"],["LICH","OGRE-MAGI","PUCK"],["LICH","OGRE-MAGI","RAZOR"],["LICH","PUCK","RAZOR"],["LINA","OGRE-MAGI","PUCK"],["LINA","OGRE-MAGI","RAZOR"],["LINA","PUCK","RAZOR"],["OGRE-MAGI","PUCK","RAZOR"]],"preCombinationsCount":35},{"count":6,"preCombinations":[["CRYSTAL-MAIDEN","KEEPER-OF-THE-LIGHT","LICH","LINA","OGRE-MAGI","PUCK"],["CRYSTAL-MAIDEN","KEEPER-OF-THE-LIGHT","LICH","LINA","OGRE-MAGI","RAZOR"],["CRYSTAL-MAIDEN","KEEPER-OF-THE-LIGHT","LICH","LINA","PUCK","RAZOR"],["CRYSTAL-MAIDEN","KEEPER-OF-THE-LIGHT","LICH","OGRE-MAGI","PUCK","RAZOR"],["CRYSTAL-MAIDEN","KEEPER-OF-THE-LIGHT","LINA","OGRE-MAGI","PUCK","RAZOR"],["CRYSTAL-MAIDEN","LICH","LINA","OGRE-MAGI","PUCK","RAZOR"],["KEEPER-OF-THE-LIGHT","LICH","LINA","OGRE-MAGI","PUCK","RAZOR"]],"preCombinationsCount":7}],"secondLevel":{"alliances":["bloodbound","dragon","elusive","heartless","human","primordial"],"heroes":["ABADDON","ANTI-MAGE","ARC-WARDEN","BLOODSEEKER","DRAGON-KNIGHT","DROW-RANGER","ENIGMA","KUNKKA","LUNA","LYCAN","MIRANA","MORPHLING","NATURE'S-PROPHET","NECROPHOS","OMNIKNIGHT","PHANTOM-ASSASSIN","PUDGE","TEMPLAR-ASSASSIN","TINY","TREANT-PROTECTOR","VIPER","WARLOCK","WINDRANGER"]}}