{"name":"assassin","allianceHeroes":["BLOODSEEKER","BOUNTY-HUNTER","MORPHLING","PHANTOM-ASSASSIN","QUEEN-OF-PAIN","SAND-KING","SLARK","TEMPLAR-ASSASSIN","VIPER"],"allianceHeroesCount":9,"levels":[{"count":3,"preCombinations":[["BLOODSEEKER","BOUNTY-HUNTER","MORPHLING"],["BLOODSEEKER","BOUNTY-HUNTER","PHANTOM-ASSASSIN"],["BLOODSEEKER","BOUNTY-HUNTER","QUEEN-OF-PAIN"],["BLOODSEEKER","BOUNTY-HUNTER","SAND-KING"],["BLOODSEEKER","BOUNTY-HUNTER","SLARK"],["BLOODSEEKER","BOUNTY-HUNTER","TEMPLAR-ASSASSIN"],["BLOODSEEKER","BOUNTY-HUNTER","VIPER"],["BLOODSEEKER","MORPHLING","PHANTOM-ASSASSIN"],["BLOODSEEKER","MORPHLING","QUEEN-OF-PAIN"],["BLOODSEEKER","MORPHLING","SAND-KING"],["BLOODSEEKER","MORPHLING","SLARK"],["BLOODSEEKER","MORPHLING","TEMPLAR-ASSASSIN"],["BLOODSEEKER","MORPHLING","VIPER"],["BLOODSEEKER","PHANTOM-ASSASSIN","QUEEN-OF-PAIN"],["BLOODSEEKER","PHANTOM-ASSASSIN","SAND-KING"],["BLOODSEEKER","PHANTOM-ASSASSIN","SLARK"],["BLOODSEEKER","PHANTOM-ASSASSIN","TEMPLAR-ASSASSIN"],["BLOODSEEKER","PHANTOM-ASSASSIN","VIPER"],["BLOODSEEKER","QUEEN-OF-PAIN","SAND-KING"],["BLOODSEEKER","QUEEN-OF-PAIN","SLARK"],["BLOODSEEKER","QUEEN-OF-PAIN","TEMPLAR-ASSASSIN"],["BLOODSEEKER","QUEEN-OF-PAIN","VIPER"],["BLOODSEEKER","SAND-KING","SLARK"],["BLOODSEEKER","SAND-KING","TEMPLAR-ASSASSIN"],["BLOODSEEKER","SAND-KING","VIPER"],["BLOODSEEKER","SLARK","TEMPLAR-ASSASSIN"],["BLOODSEEKER","SLARK","VIPER"],["BLOODSEEKER","TEMPLAR-ASSASSIN","VIPER"],["BOUNTY-HUNTER","MORPHLING","PHANTOM-ASSASSIN"],["BOUNTY-HUNTER","MORPHLING","QUEEN-OF-PAIN"],["BOUNTY-HUNTER","MORPHLING","SAND-KING"],["BOUNTY-HUNTER","MORPHLING","SLARK"],["BOUNTY-HUNTER","MORPHLING","TEMPLAR-ASSASSIN"],["BOUNTY-HUNTER","MORPHLING","VIPER"],["BOUNTY-HUNTER","PHANTOM-ASSASSIN","QUEEN-OF-PAIN"],["BOUNTY-HUNTER","PHANTOM-ASSASSIN","SAND-KING"],["BOUNTY-HUNTER","PHANTOM-ASSASSIN","SLARK"],["BOUNTY-HUNTER","PHANTOM-ASSASSIN","TEMPLAR-ASSASSIN"],["BOUNTY-HUNTER","PHANTOM-ASSASSIN","VIPER"],["BOUNTY-HUNTER","QUEEN-OF-PAIN","SAND-KING"],["BOUNTY-HUNTER","QUEEN-OF-PAIN","SLARK"],["BOUNTY-HUNTER","QUEEN-OF-PAIN","TEMPLAR-ASSASSIN"],["BOUNTY-HUNTER","QUEEN-OF-PAIN","VIPER"],["BOUNTY-HUNTER","SAND-KING","SLARK"],["BOUNTY-HUNTER","SAND-KING","TEMPLAR-ASSASSIN"],["BOUNTY-HUNTER","SAND-KING","VIPER"],["BOUNTY-HUNTER","SLARK","TEMPLAR-ASSASSIN"],["BOUNTY-HUNTER","SLARK","VIPER"],["BOUNTY-HUNTER","TEMPLAR-ASSASSIN","VIPER"],["MORPHLING","PHANTOM-ASSASSIN","QUEEN-OF-PAIN"],["MORPHLING","PHANTOM-ASSASSIN","SAND-KING"],["MORPHLING","PHANTOM-ASSASSIN","SLARK"],["MORPHLING","PHANTOM-ASSASSIN","TEMPLAR-ASSASSIN"],["MORPHLING","PHANTOM-ASSASSIN","VIPER"],["MORPHLING","QUEEN-OF-PAIN","SAND-KING"],["MORPHLING","QUEEN-OF-PAIN","SLARK"],["MORPHLING","QUEEN-OF-PAIN","TEMPLAR-ASSASSIN"],["MORPHLING","QUEEN-OF-PAIN","VIPER"],["MORPHLING","SAND-KING","SLARK"],["MORPHLING","SAND-KING","TEMPLAR-ASSASSIN"],["MORPHLING","SAND-KING","VIPER"],["MORPHLING","SLARK","TEMPLAR-ASSASSIN"],["MORPHLING","SLARK","VIPER"],["MORPHLING","TEMPLAR-ASSASSIN","VIPER"],["PHANTOM-ASSASSIN","QUEEN-OF-PAIN","SAND-KING"],["PHANTOM-ASSASSIN","QUEEN-OF-PAIN","SLARK"],["PHANTOM-ASSASSIN","QUEEN-OF-PAIN","TEMPLAR-ASSASSIN"],["PHANTOM-ASSASSIN","QUEEN-OF-PAIN","VIPER"],["PHANTOM-ASSASSIN","SAND-KING","SLARK"],["PHANTOM-ASSASSIN","SAND-KING","TEMPLAR-ASSASSIN"],["PHANTOM-ASSASSIN","SAND-KING","VIPER"],["PHANTOM-ASSASSIN","SLARK","TEMPLAR-ASSASSIN"],["PHANTOM-ASSASSIN","SLARK","VIPER"],["PHANTOM-ASSASSIN","TEMPLAR-ASSASSIN","VIPER"],["QUEEN-OF-PAIN","SAND-KING","SLARK"],["QUEEN-OF-PAIN","SAND-KING","TEMPLAR-ASSASSIN"],["QUEEN-OF-PAIN","SAND-KING","VIPER"],["QUEEN-OF-PAIN","SLARK","TEMPLAR-ASSASSIN"],["QUEEN-OF-PAIN","SLARK","VIPER"],["QUEEN-OF-PAIN","TEMPLAR-ASSASSIN","VIPER"],["SAND-KING","SLARK","TEMPLAR-ASSASSIN"],["SAND-KING","SLARK","VIPER"],["SAND-KING","TEMPLAR-ASSASSIN","VIPER"],["SLARK","TEMPLAR-ASSASSIN","VIPER"]],"preCombinationsCount":84},{"count":6,"preCombinations":[["BLOODSEEKER","BOUNTY-HUNTER","MORPHLING","PHANTOM-ASSASSIN","QUEEN-OF-PAIN","SAND-KING"],["BLOODSEEKER","BOUNTY-HUNTER","MORPHLING","PHANTOM-ASSASSIN","QUEEN-OF-PAIN","SLARK"],["BLOODSEEKER","BOUNTY-HUNTER","MORPHLING","PHANTOM-ASSASSIN","QUEEN-OF-PAIN","TEMPLAR-ASSASSIN"],["BLOODSEEKER","BOUNTY-HUNTER","MORPHLING","PHANTOM-ASSASSIN","QUEEN-OF-PAIN","VIPER"],["BLOODSEEKER","BOUNTY-HUNTER","MORPHLING","PHANTOM-ASSASSIN","SAND-KING","SLARK"],["BLOODSEEKER","BOUNTY-HUNTER","MORPHLING","PHANTOM-ASSASSIN","SAND-KING","TEMPLAR-ASSASSIN"],["BLOODSEEKER","BOUNTY-HUNTER","MORPHLING","PHANTOM-ASSASSIN","SAND-KING","VIPER"],["BLOODSEEKER","BOUNTY-HUNTER","MORPHLING","PHANTOM-ASSASSIN","SLARK","TEMPLAR-ASSASSIN"],["BLOODSEEKER","BOUNTY-HUNTER","MORPHLING","PHANTOM-ASSASSIN","SLARK","VIPER"],["BLOODSEEKER","BOUNTY-HUNTER","MORPHLING","PHANTOM-ASSASSIN","TEMPLAR-ASSASSIN","VIPER"],["BLOODSEEKER","BOUNTY-HUNTER","MORPHLING","QUEEN-OF-PAIN","SAND-KING","SLARK"],["BLOODSEEKER","BOUNTY-HUNTER","MORPHLING","QUEEN-OF-PAIN","SAND-KING","TEMPLAR-ASSASSIN"],["BLOODSEEKER","BOUNTY-HUNTER","MORPHLING","QUEEN-OF-PAIN","SAND-KING","VIPER"],["BLOODSEEKER","BOUNTY-HUNTER","MORPHLING","QUEEN-OF-PAIN","SLARK","TEMPLAR-ASSASSIN"],["BLOODSEEKER","BOUNTY-HUNTER","MORPHLING","QUEEN-OF-PAIN","SLARK","VIPER"],["BLOODSEEKER","BOUNTY-HUNTER","MORPHLING","QUEEN-OF-PAIN","TEMPLAR-ASSASSIN","VIPER"],["BLOODSEEKER","BOUNTY-HUNTER","MORPHLING","SAND-KING","SLARK","TEMPLAR-ASSASSIN"],["BLOODSEEKER","BOUNTY-HUNTER","MORPHLING","SAND-KING","SLARK","VIPER"],["BLOODSEEKER","BOUNTY-HUNTER","MORPHLING","SAND-KING","TEMPLAR-ASSASSIN","VIPER"],["BLOODSEEKER","BOUNTY-HUNTER","MORPHLING","SLARK","TEMPLAR-ASSASSIN","VIPER"],["BLOODSEEKER","BOUNTY-HUNTER","PHANTOM-ASSASSIN","QUEEN-OF-PAIN","SAND-KING","SLARK"],["BLOODSEEKER","BOUNTY-HUNTER","PHANTOM-ASSASSIN","QUEEN-OF-PAIN","SAND-KING","TEMPLAR-ASSASSIN"],["BLOODSEEKER","BOUNTY-HUNTER","PHANTOM-ASSASSIN","QUEEN-OF-PAIN","SAND-KING","VIPER"],["BLOODSEEKER","BOUNTY-HUNTER","PHANTOM-ASSASSIN","QUEEN-OF-PAIN","SLARK","TEMPLAR-ASSASSIN"],["BLOODSEEKER","BOUNTY-HUNTER","PHANTOM-ASSASSIN","QUEEN-OF-PAIN","SLARK","VIPER"],["BLOODSEEKER","BOUNTY-HUNTER","PHANTOM-ASSASSIN","QUEEN-OF-PAIN","TEMPLAR-ASSASSIN","VIPER"],["BLOODSEEKER","BOUNTY-HUNTER","PHANTOM-ASSASSIN","SAND-KING","SLARK","TEMPLAR-ASSASSIN"],["BLOODSEEKER","BOUNTY-HUNTER","PHANTOM-ASSASSIN","SAND-KING","SLARK","VIPER"],["BLOODSEEKER","BOUNTY-HUNTER","PHANTOM-ASSASSIN","SAND-KING","TEMPLAR-ASSASSIN","VIPER"],["BLOODSEEKER","BOUNTY-HUNTER","PHANTOM-ASSASSIN","SLARK","TEMPLAR-ASSASSIN","VIPER"],["BLOODSEEKER","BOUNTY-HUNTER","QUEEN-OF-PAIN","SAND-KING","SLARK","TEMPLAR-ASSASSIN"],["BLOODSEEKER","BOUNTY-HUNTER","QUEEN-OF-PAIN","SAND-KING","SLARK","VIPER"],["BLOODSEEKER","BOUNTY-HUNTER","QUEEN-OF-PAIN","SAND-KING","TEMPLAR-ASSASSIN","VIPER"],["BLOODSEEKER","BOUNTY-HUNTER","QUEEN-OF-PAIN","SLARK","TEMPLAR-ASSASSIN","VIPER"],["BLOODSEEKER","BOUNTY-HUNTER","SAND-KING","SLARK","TEMPLAR-ASSASSIN","VIPER"],["BLOODSEEKER","MORPHLING","PHANTOM-ASSASSIN","QUEEN-OF-PAIN","SAND-KING","SLARK"],["BLOODSEEKER","MORPHLING","PHANTOM-ASSASSIN","QUEEN-OF-PAIN","SAND-KING","TEMPLAR-ASSASSIN"],["BLOODSEEKER","MORPHLING","PHANTOM-ASSASSIN","QUEEN-OF-PAIN","SAND-KING","VIPER"],["BLOODSEEKER","MORPHLING","PHANTOM-ASSASSIN","QUEEN-OF-PAIN","SLARK","TEMPLAR-ASSASSIN"],["BLOODSEEKER","MORPHLING","PHANTOM-ASSASSIN","QUEEN-OF-PAIN","SLARK","VIPER"],["BLOODSEEKER","MORPHLING","PHANTOM-ASSASSIN","QUEEN-OF-PAIN","TEMPLAR-ASSASSIN","VIPER"],["BLOODSEEKER","MORPHLING","PHANTOM-ASSASSIN","SAND-KING","SLARK","TEMPLAR-ASSASSIN"],["BLOODSEEKER","MORPHLING","PHANTOM-ASSASSIN","SAND-KING","SLARK","VIPER"],["BLOODSEEKER","MORPHLING","PHANTOM-ASSASSIN","SAND-KING","TEMPLAR-ASSASSIN","VIPER"],["BLOODSEEKER","MORPHLING","PHANTOM-ASSASSIN","SLARK","TEMPLAR-ASSASSIN","VIPER"],["BLOODSEEKER","MORPHLING","QUEEN-OF-PAIN","SAND-KING","SLARK","TEMPLAR-ASSASSIN"],["BLOODSEEKER","MORPHLING","QUEEN-OF-PAIN","SAND-KING","SLARK","VIPER"],["BLOODSEEKER","MORPHLING","QUEEN-OF-PAIN","SAND-KING","TEMPLAR-ASSASSIN","VIPER"],["BLOODSEEKER","MORPHLING","QUEEN-OF-PAIN","SLARK","TEMPLAR-ASSASSIN","VIPER"],["BLOODSEEKER","MORPHLING","SAND-KING","SLARK","TEMPLAR-ASSASSIN","VIPER"],["BLOODSEEKER","PHANTOM-ASSASSIN","QUEEN-OF-PAIN","SAND-KING","SLARK","TEMPLAR-ASSASSIN"],["BLOODSEEKER","PHANTOM-ASSASSIN","QUEEN-OF-PAIN","SAND-KING","SLARK","VIPER"],["BLOODSEEKER","PHANTOM-ASSASSIN","QUEEN-OF-PAIN","SAND-KING","TEMPLAR-ASSASSIN","VIPER"],["BLOODSEEKER","PHANTOM-ASSASSIN","QUEEN-OF-PAIN","SLARK","TEMPLAR-ASSASSIN","VIPER"],["BLOODSEEKER","PHANTOM-ASSASSIN","SAND-KING","SLARK","TEMPLAR-ASSASSIN","VIPER"],["BLOODSEEKER","QUEEN-OF-PAIN","SAND-KING","SLARK","TEMPLAR-ASSASSIN","VIPER"],["BOUNTY-HUNTER","MORPHLING","PHANTOM-ASSASSIN","QUEEN-OF-PAIN","SAND-KING","SLARK"],["BOUNTY-HUNTER","MORPHLING","PHANTOM-ASSASSIN","QUEEN-OF-PAIN","SAND-KING","TEMPLAR-ASSASSIN"],["BOUNTY-HUNTER","MORPHLING","PHANTOM-ASSASSIN","QUEEN-OF-PAIN","SAND-KING","VIPER"],["BOUNTY-HUNTER","MORPHLING","PHANTOM-ASSASSIN","QUEEN-OF-PAIN","SLARK","TEMPLAR-ASSASSIN"],["BOUNTY-HUNTER","MORPHLING","PHANTOM-ASSASSIN","QUEEN-OF-PAIN","SLARK","VIPER"],["BOUNTY-HUNTER","MORPHLING","PHANTOM-ASSASSIN","QUEEN-OF-PAIN","TEMPLAR-ASSASSIN","VIPER"],["BOUNTY-HUNTER","MORPHLING","PHANTOM-ASSASSIN","SAND-KING","SLARK","TEMPLAR-ASSASSIN"],["BOUNTY-HUNTER","MORPHLING","PHANTOM-ASSASSIN","SAND-KING","SLARK","VIPER"],["BOUNTY-HUNTER","MORPHLING","PHANTOM-ASSASSIN","SAND-KING","TEMPLAR-ASSASSIN","VIPER"],["BOUNTY-HUNTER","MORPHLING","PHANTOM-ASSASSIN","SLARK","TEMPLAR-ASSASSIN","VIPER"],["BOUNTY-HUNTER","MORPHLING","QUEEN-OF-PAIN","SAND-KING","SLARK","TEMPLAR-ASSASSIN"],["BOUNTY-HUNTER","MORPHLING","QUEEN-OF-PAIN","SAND-KING","SLARK","VIPER"],["BOUNTY-HUNTER","MORPHLING","QUEEN-OF-PAIN","SAND-KING","TEMPLAR-ASSASSIN","VIPER"],["BOUNTY-HUNTER","MORPHLING","QUEEN-OF-PAIN","SLARK","TEMPLAR-ASSASSIN","VIPER"],["BOUNTY-HUNTER","MORPHLING","SAND-KING","SLARK","TEMPLAR-ASSASSIN","VIPER"],["BOUNTY-HUNTER","PHANTOM-ASSASSIN","QUEEN-OF-PAIN","SAND-KING","SLARK","TEMPLAR-ASSASSIN"],["BOUNTY-HUNTER","PHANTOM-ASSASSIN","QUEEN-OF-PAIN","SAND-KING","SLARK","VIPER"],["BOUNTY-HUNTER","PHANTOM-ASSASSIN","QUEEN-OF-PAIN","SAND-KING","TEMPLAR-ASSASSIN","VIPER"],["BOUNTY-HUNTER","PHANTOM-ASSASSIN","QUEEN-OF-PAIN","SLARK","TEMPLAR-ASSASSIN","VIPER"],["BOUNTY-HUNTER","PHANTOM-ASSASSIN","SAND-KING","SLARK","TEMPLAR-ASSASSIN","VIPER"],["BOUNTY-HUNTER","QUEEN-OF-PAIN","SAND-KING","SLARK","TEMPLAR-ASSASSIN","VIPER"],["MORPHLING","PHANTOM-ASSASSIN","QUEEN-OF-PAIN","SAND-KING","SLARK","TEMPLAR-ASSASSIN"],["MORPHLING","PHANTOM-ASSASSIN","QUEEN-OF-PAIN","SAND-KING","SLARK","VIPER"],["MORPHLING","PHANTOM-ASSASSIN","QUEEN-OF-PAIN","SAND-KING","TEMPLAR-ASSASSIN","VIPER"],["MORPHLING","PHANTOM-ASSASSIN","QUEEN-OF-PAIN","SLARK","TEMPLAR-ASSASSIN","VIPER"],["MORPHLING","PHANTOM-ASSASSIN","SAND-KING","SLARK","TEMPLAR-ASSASSIN","VIPER"],["MORPHLING","QUEEN-OF-PAIN","SAND-KING","SLARK","TEMPLAR-ASSASSIN","VIPER"],["PHANTOM-ASSASSIN","QUEEN-OF-PAIN","SAND-KING","SLARK","TEMPLAR-ASSASSIN","VIPER"]],"preCombinationsCount":84},{"count":9,"preCombinations":[["BLOODSEEKER","BOUNTY-HUNTER","MORPHLING","PHANTOM-ASSASSIN","QUEEN-OF-PAIN","SAND-KING","SLARK","TEMPLAR-ASSASSIN","VIPER"]],"preCombinationsCount":1}],"secondLevel":{"alliances":["demon","dragon","elusive","human","primordial","savage","scaled","scrappy"],"heroes":["ALCHEMIST","ANTI-MAGE","ARC-WARDEN","CHAOS-KNIGHT","CLOCKWERK","CRYSTAL-MAIDEN","DOOM","DRAGON-KNIGHT","ENCHANTRESS","ENIGMA","KEEPER-OF-THE-LIGHT","KUNKKA","LINA","LONE-DRUID","LUNA","LYCAN","MEDUSA","MIRANA","NATURE'S-PROPHET","OMNIKNIGHT","PUCK","RAZOR","SHADOW-FIEND","SLARDAR","TECHIES","TERRORBLADE","TIDEHUNTER","TIMBERSAW","TINKER","TINY","TREANT-PROTECTOR","TUSK","VENOMANCER","WINDRANGER"]}}